highcharts_excentis/__init__.py
highcharts_excentis/ipynb.py
highcharts_excentis/version.py
highcharts_excentis/highcharts/__init__.py
highcharts_excentis/highcharts/common.py
highcharts_excentis/highcharts/highchart_types.py
highcharts_excentis/highcharts/highcharts.py
highcharts_excentis/highcharts/options.py
highcharts_excentis/highcharts/templates/base.html
highcharts_excentis/highcharts/templates/content.html
highcharts_excentis/highcharts/templates/page.html
highcharts_excentis/highcharts/templates/test.html
highcharts_excentis/highmaps/__init__.py
highcharts_excentis/highmaps/common.py
highcharts_excentis/highmaps/highmap_helper.py
highcharts_excentis/highmaps/highmap_types.py
highcharts_excentis/highmaps/highmaps.py
highcharts_excentis/highmaps/options.py
highcharts_excentis/highmaps/templates/base.html
highcharts_excentis/highmaps/templates/content.html
highcharts_excentis/highmaps/templates/page.html
highcharts_excentis/highmaps/templates/test.html
highcharts_excentis/highstock/__init__.py
highcharts_excentis/highstock/common.py
highcharts_excentis/highstock/highstock.py
highcharts_excentis/highstock/highstock_helper.py
highcharts_excentis/highstock/highstock_types.py
highcharts_excentis/highstock/options.py
highcharts_excentis/highstock/templates/base.html
highcharts_excentis/highstock/templates/content.html
highcharts_excentis/highstock/templates/page.html
highcharts_excentis/highstock/templates/test.html
highcharts_excentis-0.4.6.dist-info/licenses/LICENSE
highcharts_excentis-0.4.6.dist-info/METADATA
highcharts_excentis-0.4.6.dist-info/WHEEL
highcharts_excentis-0.4.6.dist-info/top_level.txt
highcharts_excentis-0.4.6.dist-info/RECORD
