Metadata-Version: 2.4
Name: highcharts-excentis
Version: 0.4.6
Summary: Python Highcharts wrapper
Author-email: Kyper Developers <developers@kyperdata.com>
Maintainer-email: Excentis Development Team <support@excentis.com>, Tom Ghyselinck <tom.ghyselinck@excentis.com>
License: Copyright (c) 2015 Kyper Data Technologies
Project-URL: Homepage, https://github.com/excentis/python-highcharts
Keywords: python,ipython,highcharts,chart,visualization,graph,javascript,html
Classifier: Framework :: IPython
Classifier: Intended Audience :: Developers
Classifier: Intended Audience :: Financial and Insurance Industry
Classifier: Intended Audience :: Science/Research
Classifier: License :: OSI Approved :: MIT License
Classifier: Programming Language :: Python
Classifier: Programming Language :: Python :: 3
Requires-Python: >=3.4
License-File: LICENSE
Requires-Dist: future
Requires-Dist: diskcache
Requires-Dist: Jinja2
Dynamic: license-file
